LICENSE
MANIFEST.in
README.md
settings.ini
setup.py
drugpri/__init__.py
drugpri/_modidx.py
drugpri/core.py
drugpri.egg-info/PKG-INFO
drugpri.egg-info/SOURCES.txt
drugpri.egg-info/dependency_links.txt
drugpri.egg-info/entry_points.txt
drugpri.egg-info/not-zip-safe
drugpri.egg-info/requires.txt
drugpri.egg-info/top_level.txt