Metadata-Version: 2.1
Name: drugpri
Version: 0.0.0
Summary: Drug prioritization workflow
Home-page: https://github.com/rraadd88/drugpri/
Author: Rohan Dandage
Author-email: rohanadandage@gmail.com
License: Apache Software License 2.0
Keywords: drugs,drug-screen,chemical interactions
Classifier: Development Status :: 3 - Alpha
Classifier: Intended Audience :: Developers
Classifier: Natural Language :: English
Classifier: Programming Language :: Python :: 3.7
Classifier: Programming Language :: Python :: 3.8
Classifier: Programming Language :: Python :: 3.9
Classifier: Programming Language :: Python :: 3.10
Classifier: License :: OSI Approved :: Apache Software License
Requires-Python: >=3.7
License-File: LICENSE
Provides-Extra: dev
